data_recorder/__init__.py
data_recorder/datarecorder.py
data_recorder-0.1.1602852884.dist-info/METADATA
data_recorder-0.1.1602852884.dist-info/WHEEL
data_recorder-0.1.1602852884.dist-info/top_level.txt
data_recorder-0.1.1602852884.dist-info/RECORD
