Metadata-Version: 2.1
Name: data-recorder
Version: 0.1.1602852884
Summary: data recorder
Home-page: https://github.com/JulianKimmig/data_recorder
Author: Julian Kimmig
Author-email: julian-kimmig@gmx.net
License: UNKNOWN
Platform: UNKNOWN
Classifier: Programming Language :: Python :: 3
Classifier: License :: OSI Approved :: MIT License
Classifier: Operating System :: OS Independent
Requires-Dist: numpy
Requires-Dist: pandas
